LogAssist/__init__.py
LogAssist/log.py
logassist-1.1.2.dist-info/licenses/LICENSE
logassist-1.1.2.dist-info/METADATA
logassist-1.1.2.dist-info/WHEEL
logassist-1.1.2.dist-info/top_level.txt
logassist-1.1.2.dist-info/RECORD
