Metadata-Version: 2.4
Name: LogAssist
Version: 1.1.2
Summary: A simple and customizable logging library for Python.
Home-page: https://github.com/horrible-gh/LogAssist.git
Author: horrible-gh
Author-email: horrible <shinjpn1@gmail.com>
Project-URL: Homepage, https://github.com/horrible-gh/Logger
Project-URL: Bug Tracker, https://github.com/horrible-gh/Logger/issues
Keywords: LogAssist,Log Assist,logassist,log assist,Logger,logger
Classifier: Programming Language :: Python :: 3
Classifier: License :: OSI Approved :: MIT License
Classifier: Operating System :: OS Independent
Requires-Python: >=3.6
License-File: LICENSE
Dynamic: author
Dynamic: home-page
Dynamic: license-file
Dynamic: requires-python
